cesium/__init__.py
cesium/data_management.py
cesium/featurize.py
cesium/time_series.py
cesium/util.py
cesium/version.py
cesium/datasets/__init__.py
cesium/datasets/andrzejak.py
cesium/datasets/asas_training.py
cesium/datasets/util.py
cesium/datasets/tests/test_datasets.py
cesium/features/__init__.py
cesium/features/_eigs.h
cesium/features/_lomb_scargle.c
cesium/features/_lomb_scargle.cp311-win_amd64.pyd
cesium/features/_lomb_scargle.h
cesium/features/_lomb_scargle.pxd
cesium/features/_lomb_scargle.pyx
cesium/features/amplitude.py
cesium/features/cadence_features.py
cesium/features/common_functions.py
cesium/features/graphs.py
cesium/features/lomb_scargle.py
cesium/features/lomb_scargle_fast.py
cesium/features/num_alias.py
cesium/features/period_folding.py
cesium/features/periodic_model.py
cesium/features/qso_model.py
cesium/features/scatter_res_raw.py
cesium/features/stetson.py
cesium/features/tests/__init__.py
cesium/features/tests/test_cadence_features.py
cesium/features/tests/test_general_features.py
cesium/features/tests/test_graphs.py
cesium/features/tests/test_lomb_scargle_features.py
cesium/features/tests/util.py
cesium/features/tests/data/245486.dat
cesium/features/tests/data/247327.dat
cesium/features/tests/data/257141.dat
cesium/features/tests/data/expected_features.csv
cesium/tests/__init__.py
cesium/tests/fixtures.py
cesium/tests/test_data_management.py
cesium/tests/test_featurize.py
cesium/tests/test_time_series.py
cesium/tests/test_util.py
cesium/tests/data/215153_215176_218272_218934.tar.gz
cesium/tests/data/215153_215176_218272_218934_metadata.dat
cesium/tests/data/247327.dat
cesium/tests/data/asas_training_subset.tar.gz
cesium/tests/data/asas_training_subset_classes_with_metadata.dat
cesium/tests/data/dotastro_215153.dat
cesium/tests/data/test_features_with_targets.csv
cesium-0.12.4.dist-info/LICENSE.txt
cesium-0.12.4.dist-info/METADATA
cesium-0.12.4.dist-info/WHEEL
cesium-0.12.4.dist-info/top_level.txt
cesium-0.12.4.dist-info/RECORD
