Metadata-Version: 2.2
Name: cesium
Version: 0.12.4
Summary: Library for time-series feature extraction and processing
Author: cesium team
Author-email: Stéfan van der Walt <stefanv@berkeley.edu>
License: BSD-3-Clause
Project-URL: homepage, http://cesium-ml.org
Project-URL: download, https://github.com/cesium-ml/cesium
Classifier: Development Status :: 4 - Beta
Classifier: Environment :: Console
Classifier: Intended Audience :: Developers
Classifier: Intended Audience :: Science/Research
Classifier: License :: OSI Approved :: BSD License
Classifier: Programming Language :: C
Classifier: Programming Language :: Python :: 3
Classifier: Topic :: Scientific/Engineering
Classifier: Operating System :: Microsoft :: Windows
Classifier: Operating System :: POSIX
Classifier: Operating System :: Unix
Classifier: Operating System :: MacOS
Requires-Python: >=3.8
License-File: LICENSE.txt
Requires-Dist: numpy<3.0,>=2.0
Requires-Dist: scipy>=0.16.0
Requires-Dist: scikit-learn>=0.22.1
Requires-Dist: pandas>=0.17.0
Requires-Dist: dask>=2.5.0
Requires-Dist: toolz
Requires-Dist: gatspy>=0.3.0
Requires-Dist: cloudpickle
Requires-Dist: joblib>=0.14.1
